<?xml version="1.0" encoding="UTF-8"?>
<catalogue>
    <figure>
        <name>Блок</name>
        <nameEng>Block</nameEng>
        <width>2</width>
        <height>2</height>
        <type>STABLE</type>
        <group>NONE</group>
        <view>
            ##
            ##
        </view>
    </figure>
    <figure>
        <name>Ромб</name>
        <nameEng>Rhombus</nameEng>
        <width>3</width>
        <height>3</height>
        <type>STABLE</type>
        <group>NONE</group>
        <view>
            _#_
            #_#
            _#_
        </view>
    </figure>
    <figure>
        <name>Левонаправленный глайдер</name>
        <nameEng>Left direction glider</nameEng>
        <width>3</width>
        <height>3</height>
        <type>RUN</type>
        <group>GLIDERS</group>
        <view>
            _#_
            #__
            ###
        </view>
    </figure>
    <figure>
        <name>Right direction glider</name>
        <nameEng>Right-hand glider</nameEng>
        <width>3</width>
        <height>3</height>
        <type>RUN</type>
        <group>GLIDERS</group>
        <view>
            _#_
            __#
            ###
        </view>
    </figure>
    <figure>
        <name>Верхненаправленный глайдер</name>
        <nameEng>Up direction glider</nameEng>
        <width>3</width>
        <height>3</height>
        <type>RUN</type>
        <group>GLIDERS</group>
        <view>
            ##_
            #_#
            #__
        </view>
    </figure>
    <figure>
        <name>Нижненаправленный глайдер</name>
        <nameEng>Down direction glider</nameEng>
        <width>3</width>
        <height>3</height>
        <type>RUN</type>
        <group>GLIDERS</group>
        <view>
            #__
            #_#
            ##_
        </view>
    </figure>
</catalogue>